README.rst
setup.py
expiringdict/__init__.py
expiringdict.egg-info/PKG-INFO
expiringdict.egg-info/SOURCES.txt
expiringdict.egg-info/dependency_links.txt
expiringdict.egg-info/requires.txt
expiringdict.egg-info/top_level.txt
expiringdict.egg-info/zip-safe