Metadata-Version: 1.0
Name: expiringdict
Version: 1.1
Summary: Dictionary with auto-expiring values for caching purposes
Home-page: https://github.com/mailgun/expiringdict
Author: Anton Efimenko
Author-email: anton@mailgunhq.com
License: Apache 2
Platform: UNKNOWN
